xargcomplete/__init__.py
xargcomplete/attribute.py
xargcomplete/command.py
xargcomplete/complete.py
xargcomplete-0.2.dist-info/LICENSE
xargcomplete-0.2.dist-info/METADATA
xargcomplete-0.2.dist-info/WHEEL
xargcomplete-0.2.dist-info/entry_points.txt
xargcomplete-0.2.dist-info/top_level.txt
xargcomplete-0.2.dist-info/zip-safe
xargcomplete-0.2.dist-info/RECORD
