Metadata-Version: 2.1
Name: xargcomplete
Version: 0.2
Summary: Tab completion management
Home-page: https://github.com/bondbox/xargcomplete/
Author: Mingzhe Zou
Author-email: zoumingzhe@outlook.com
License: GPLv2
Project-URL: Source Code, https://github.com/bondbox/xargcomplete/
Project-URL: Bug Tracker, https://github.com/bondbox/xargcomplete/issues
Project-URL: Documentation, https://github.com/bondbox/xargcomplete/
Keywords: command-line,argparse,argcomplete,completion,tab-completion
Platform: any
Classifier: Programming Language :: Python
Classifier: Programming Language :: Python :: 3
Requires-Python: >=3.8
License-File: LICENSE
Requires-Dist: xkits-command >=0.4
Requires-Dist: tabulate
Requires-Dist: pip
